pyaud/__init__.py
pyaud/__main__.py
pyaud/_builtins.py
pyaud/_cachedir.py
pyaud/_config.py
pyaud/_core.py
pyaud/_files.py
pyaud/_main.py
pyaud/_objects.py
pyaud/_version.py
pyaud/exceptions.py
pyaud/messages.py
pyaud/plugins.py
pyaud/py.typed
pyaud-8.0.0.dist-info/LICENSE
pyaud-8.0.0.dist-info/METADATA
pyaud-8.0.0.dist-info/WHEEL
pyaud-8.0.0.dist-info/entry_points.txt
pyaud-8.0.0.dist-info/RECORD
