Metadata-Version: 2.3
Name: pyaud
Version: 8.0.0
Summary: Framework for writing Python package audits
License: MIT
Keywords: audit,ci,fix,format,style
Author: jshwi
Author-email: stephen@jshwisolutions.com
Maintainer: jshwi
Maintainer-email: stephen@jshwisolutions.com
Requires-Python: >=3.9,<4.0
Classifier: License :: OSI Approved :: MIT License
Classifier: Programming Language :: Python :: 3
Classifier: Programming Language :: Python :: 3.9
Classifier: Programming Language :: Python :: 3.10
Classifier: Programming Language :: Python :: 3.11
Classifier: Programming Language :: Python :: 3.12
Classifier: Programming Language :: Python :: 3.13
Requires-Dist: arcon (>=0.3.1)
Requires-Dist: gitpython (>=3.1.30,<4.0.0)
Requires-Dist: lsfiles (>=0.5)
Requires-Dist: marshmallow (==3.19.0)
Requires-Dist: object-colors (>=2.0.1,<3.0.0)
Requires-Dist: pyaud-plugins (>=0.22.0)
Requires-Dist: rich (>=13.5.2,<14.0.0)
Project-URL: Documentation, https://pyaud.readthedocs.io/en/latest
Project-URL: Homepage, https://pypi.org/project/pyaud/
Project-URL: Repository, https://github.com/jshwi/pyaud
